delm/__init__.py
delm/config.py
delm/constants.py
delm/delm.py
delm/exceptions.py
delm/logging.py
delm/models.py
delm/core/__init__.py
delm/core/data_processor.py
delm/core/experiment_manager.py
delm/core/extraction_manager.py
delm/schemas/__init__.py
delm/schemas/schemas.py
delm/strategies/__init__.py
delm/strategies/data_loaders.py
delm/strategies/scoring_strategies.py
delm/strategies/splitting_strategies.py
delm/utils/__init__.py
delm/utils/concurrent_processing.py
delm/utils/cost_estimation.py
delm/utils/cost_tracker.py
delm/utils/model_price_database.py
delm/utils/performance_estimation.py
delm/utils/post_processing.py
delm/utils/rate_limiter.py
delm/utils/retry_handler.py
delm/utils/semantic_cache.py
delm/utils/type_checks.py
delm-1.0.1.dist-info/licenses/LICENSE.md
delm-1.0.1.dist-info/METADATA
delm-1.0.1.dist-info/WHEEL
delm-1.0.1.dist-info/top_level.txt
delm-1.0.1.dist-info/RECORD
