Metadata-Version: 2.4
Name: delm
Version: 1.0.1
Summary: DELM:Data Extraction with Language Models
Author: Eric Fithian, Kirill Skobelev
License: MIT
Project-URL: Homepage, https://github.com/Center-for-Applied-AI/delm
Project-URL: Repository, https://github.com/Center-for-Applied-AI/delm/
Project-URL: Documentation, https://center-for-applied-ai.github.io/delm/
Project-URL: Issues, https://github.com/Center-for-Applied-AI/delm/issues
Classifier: Development Status :: 3 - Alpha
Classifier: Intended Audience :: Developers
Classifier: Intended Audience :: Science/Research
Classifier: Programming Language :: Python :: 3
Classifier: Programming Language :: Python :: 3.10
Classifier: Programming Language :: Python :: 3.11
Classifier: Topic :: Scientific/Engineering :: Artificial Intelligence
Classifier: Topic :: Text Processing :: Linguistic
Requires-Python: >=3.10
License-File: LICENSE.md
Requires-Dist: pandas>=1.5.0
Requires-Dist: numpy>=1.21.0
Requires-Dist: pyarrow>=7.0.0
Requires-Dist: instructor>=0.4.0
Requires-Dist: pydantic>=2.0.0
Requires-Dist: pyyaml>=6.0
Requires-Dist: tqdm>=4.64.0
Requires-Dist: rapidfuzz>=3.0.0
Requires-Dist: beautifulsoup4>=4.11.0
Requires-Dist: python-docx>=0.8.11
Requires-Dist: tiktoken>=0.5.0
Provides-Extra: extras
Requires-Dist: marker-pdf>=0.1.0; extra == "extras"
Requires-Dist: openpyxl>=3.0.0; extra == "extras"
Requires-Dist: zstandard>=0.21.0; extra == "extras"
Requires-Dist: lmdb>=1.3.0; extra == "extras"
Provides-Extra: dev
Requires-Dist: pytest>=7.0.0; extra == "dev"
Requires-Dist: pytest-cov>=4.0.0; extra == "dev"
Requires-Dist: black>=22.0.0; extra == "dev"
Requires-Dist: flake8>=5.0.0; extra == "dev"
Requires-Dist: mypy>=1.0.0; extra == "dev"
Requires-Dist: mkdocs-material>=9.0.0; extra == "dev"
Provides-Extra: examples
Requires-Dist: scikit-learn>=1.1.0; extra == "examples"
Requires-Dist: matplotlib>=3.5.0; extra == "examples"
Requires-Dist: seaborn>=0.11.0; extra == "examples"
Dynamic: license-file
